gsbparse/__init__.py
gsbparse/account_file.py
gsbparse/account_section.py
gsbparse/transactions.py
gsbparse-0.3.0.dist-info/LICENSE.txt
gsbparse-0.3.0.dist-info/METADATA
gsbparse-0.3.0.dist-info/WHEEL
gsbparse-0.3.0.dist-info/top_level.txt
gsbparse-0.3.0.dist-info/RECORD
