Metadata-Version: 2.1
Name: gsbparse
Version: 0.3.0
Summary: A simple parser for your Grisbi's .gsb account files
Home-page: https://github.com/EBoisseauSierra/gsbparse
Author: Étienne Boisseau-Sierra
Author-email: etienne.boisseau.sierra@gmail.com
Maintainer: Étienne Boisseau-Sierra
Maintainer-email: etienne.boisseau.sierra@gmail.com
License: MIT
Classifier: License :: OSI Approved :: MIT License
Classifier: Operating System :: OS Independent
Classifier: Programming Language :: Python :: 3
Classifier: Programming Language :: Python :: 3.9
Requires-Python: >=3.9
License-File: LICENSE.txt
Requires-Dist: defusedxml
Requires-Dist: pandas
Provides-Extra: dev
Requires-Dist: black ; extra == 'dev'
Requires-Dist: flake8 ; extra == 'dev'
Requires-Dist: pre-commit ; extra == 'dev'
Requires-Dist: pylint ; extra == 'dev'
Provides-Extra: test
Requires-Dist: pytest ; extra == 'test'
Requires-Dist: pytest-cov ; extra == 'test'
